stallion/__init__.py
stallion/client.py
stallion/message.py
stallion/network.py
stallion/stringparser.py
stallion_python_sdk-1.2.4.dist-info/LICENSE.txt
stallion_python_sdk-1.2.4.dist-info/METADATA
stallion_python_sdk-1.2.4.dist-info/WHEEL
stallion_python_sdk-1.2.4.dist-info/top_level.txt
stallion_python_sdk-1.2.4.dist-info/RECORD
