Metadata-Version: 2.1
Name: stallion-python-sdk
Version: 1.2.4
Summary: SDK for Stallion message broker
Home-page: https://github.com/amirhnajafiz/stallion-python-sdk
Author: amirhnajafiz
Author-email: najafizadeh21@gmail.com
Classifier: Programming Language :: Python :: 3
Classifier: License :: OSI Approved :: MIT License
Classifier: Operating System :: OS Independent
Requires-Python: >=3.6
License-File: LICENSE.txt
